puya_rsa/__init__.py
puya_rsa/py.typed
puya_rsa/rsa.py
puya_rsa-0.2.2.dist-info/LICENSE
puya_rsa-0.2.2.dist-info/METADATA
puya_rsa-0.2.2.dist-info/WHEEL
puya_rsa-0.2.2.dist-info/RECORD
