Metadata-Version: 2.1
Name: puya-rsa
Version: 0.2.2
Summary: Algorand Puya RSA Signature Verification: RFC8017 RSASSA-PKCS1-V1.5-VERIFY function implementation
Home-page: https://github.com/Helium-Labs/Puya-RSA
License: GNU GPLv3
Author: Winton Nathan-Roberts
Author-email: winton.nathan.roberts@gmail.com
Requires-Python: >=3.12,<4.0
Classifier: License :: Other/Proprietary License
Classifier: Programming Language :: Python :: 3
Classifier: Programming Language :: Python :: 3.12
Requires-Dist: algorand-python (>=2.0.1,<3.0.0)
Requires-Dist: puya-bignumber (==0.4.1)
Requires-Dist: puyapy (>=3.1.0,<4.0.0)
Requires-Dist: py-algorand-sdk (>=2.6.1,<3.0.0)
Project-URL: Repository, https://github.com/Helium-Labs/Puya-RSA
